Workbook

Sheet Cover
B3: SOLUSINDO PREMIER
B4: LAPORAN KEUANGAN PROYEK LELANG
B5: Untuk Pemegang Saham & Investor
B9: ID PROYEK | D9: [FLPxxxx]
B11: IDENTITAS PROYEK
B13: Nama Proyek | D13: [nama_project]
B14: Alamat Properti | D14: [alamat_property]
B15: Lokasi | D15: [kota, kecamatan, kelurahan, provinsi]
B16: Tanggal Pembelian | D16: [tanggal_pembelian]
B17: Tanggal Mulai | D17: [mulai_tanggal]
B18: Estimasi Selesai | D18: [estimasi_selesai]
B19: Estimasi Durasi | D19: [estimasi_bulan (bulan)]
B20: Status Proyek | D20: [status]
B21: Jenis Pendanaan | D21: [jenis_pendanaan]
B22: Penanggung Jawab | D22: [dibuat_oleh (Agent)]
B25: RINGKASAN INVESTASI
B27: Harga Pembelian | D27: Estimasi Harga Jual | F27: Estimasi Profit Bersih
B28: ='Profil Proyek'!D9 | D28: ='Profil Proyek'!D10 | F28: ='Profil Proyek'!D11
B32: Dokumen ini bersifat rahasia dan diperuntukkan bagi pemegang saham, investor, dan manajemen Solusindo Premier.
B33: Sel berwarna BIRU adalah data export dari database. Sel HITAM adalah hasil kalkulasi otomatis.

Sheet Profil Proyek
B2: PROFIL & VALUASI PROYEK
B5: ▎ VALUASI PROPERTI
B7: Komponen | C7: Field Database | D7: Nilai (Rp) | E7: % dari Harga Jual
B9: Harga Pembelian Properti | C9: harga_pembelian | D9: 0 | E9: =IFERROR(D9/$D$10,0)
B10: Estimasi Harga Jual | C10: estimasi_harga_jual | D10: 0 | E10: =IFERROR(D10/$D$10,0)
B11: Estimasi Profit Bersih | C11: estimasi_profit_bersih | D11: 0 | E11: =IFERROR(D11/$D$10,0)
B13: ▎ BREAKDOWN BIAYA AKUISISI
B14: Komponen Biaya | C14: Field Database | D14: Nilai (Rp) | E14: % Komposisi
B15: ● Nilai Limit Lelang | C15: nilai_limit_lelang → Utama | D15: 0 | E15: =IFERROR(D15/$D$21,0)
B16: ● Spare Bidding | C16: spare_bidding → Utama | D16: 0 | E16: =IFERROR(D16/$D$21,0)
B17: ● Biaya Eksekusi | C17: biaya_eksekusi → Utama | D17: 0 | E17: =IFERROR(D17/$D$21,0)
B18: ● Biaya Balik Nama | C18: biaya_balik_nama → Dokumen | D18: 0 | E18: =IFERROR(D18/$D$21,0)
B19: ● Biaya Renovasi | C19: biaya_renov → Renovasi | D19: 0 | E19: =IFERROR(D19/$D$21,0)
B20: ● Dana Cadangan | C20: dana_cadangan → Cadangan | D20: 0 | E20: =IFERROR(D20/$D$21,0)
B21: TOTAL BIAYA AKUISISI | C21: total_biaya_akuisisi | D21: =SUM(D15:D20) | E21: 100.0%
B23: ▎ STATUS PENDANAAN
B24: Komponen | C24: Field Database | D24: Nilai (Rp) | E24: % Pencapaian
B25: Target Pendanaan | C25: target_pendanaan | D25: 0 | E25: 100.0%
B26: Total Pendanaan Terkumpul | C26: total_pendanaan | D26: 0 | E26: =IFERROR(D26/D25,0)
B27: Selisih (Gap Pendanaan) | C27: Target − Terkumpul (otomatis) | D27: =D25-D26 | E27: =IFERROR(D27/D25,0)
B29: ▎ PROYEKSI ROI
B31: Komponen | C31: Nilai (Rp)
B32: Harga Pembelian | C32: =D9
B33: Total Biaya Akuisisi | C33: =D21
B34: Estimasi Harga Jual | C34: =D10
B35: Estimasi Profit | C35: =D11
B37: ROI % | D37: Margin Jual | F37: Markup
B38: =IFERROR(D11/D21,0) | D38: =IFERROR(D11/D10,0) | F38: =IFERROR((D10-D21)/D21,0)

Sheet Ringkasan Eksekutif
B2: RINGKASAN EKSEKUTIF
B5: TOTAL ANGGARAN | D5: TOTAL REALISASI | E5: % PENYERAPAN | G5: SISA ANGGARAN
B6: ='Anggaran vs Realisasi'!D10 | D6: ='Anggaran vs Realisasi'!E10 | E6: =IFERROR('Anggaran vs Realisasi'!E10/'Anggaran vs Realisasi'!D10,0) | G6: ='Anggaran vs Realisasi'!F10
B7: Plafon disetujui | D7: Pengeluaran aktual | E7: Realisasi / Anggaran | G7: Surplus / (Defisit)
B9: ▎ ARUS KAS PROYEK
B11: TOTAL PEMASUKAN | D11: TOTAL PENGELUARAN | F11: NET CASHFLOW
B12: =SUMPRODUCT(('Cashflow Timeline'!E7:E106="pemasukan")*'Cashflow Timeline'!G7:G106) | D12: =SUMPRODUCT(('Cashflow Timeline'!E7:E106="pengeluaran")*'Cashflow Timeline'!G7:G106) | F12: =B12-D12
B14: ▎ RINGKASAN PER DOMPET
B16: Dompet | C16: Sumber Anggaran | D16: Anggaran (Rp) | E16: Realisasi (Rp) | F16: Sisa (Rp) | G16: % Pakai | H16: Status
B17: Utama | C17: Limit Lelang + Spare Bidding + Biaya Eksekusi | D17: ='Dompet Utama'!E5 | E17: ='Dompet Utama'!E6 | F17: =D17-E17 | G17: =IFERROR(E17/D17,0) | H17: =IF(D17=0,"-",IF(E17>D17,"OVER BUDGET",IF(E17/D17>=0.9,"WASPADA","AMAN")))
B18: Dokumen | C18: Biaya Balik Nama (Notaris, BPN, Pajak) | D18: ='Dompet Dokumen'!E5 | E18: ='Dompet Dokumen'!E6 | F18: =D18-E18 | G18: =IFERROR(E18/D18,0) | H18: =IF(D18=0,"-",IF(E18>D18,"OVER BUDGET",IF(E18/D18>=0.9,"WASPADA","AMAN")))
B19: Renovasi | C19: Renovasi & Peningkatan Properti | D19: ='Dompet Renovasi'!E5 | E19: ='Dompet Renovasi'!E6 | F19: =D19-E19 | G19: =IFERROR(E19/D19,0) | H19: =IF(D19=0,"-",IF(E19>D19,"OVER BUDGET",IF(E19/D19>=0.9,"WASPADA","AMAN")))
B20: Cadangan | C20: Dana Cadangan / Kontingensi | D20: ='Dompet Cadangan'!E5 | E20: ='Dompet Cadangan'!E6 | F20: =D20-E20 | G20: =IFERROR(E20/D20,0) | H20: =IF(D20=0,"-",IF(E20>D20,"OVER BUDGET",IF(E20/D20>=0.9,"WASPADA","AMAN")))
B21: TOTAL | C21: Seluruh Dompet | D21: =SUM(D17:D20) | E21: =SUM(E17:E20) | F21: =D21-E21 | G21: =IFERROR(E21/D21,0) | H21: =IF(D21=0,"-",IF(E21>D21,"OVER BUDGET",IF(E21/D21>=0.9,"WASPADA","AMAN")))
B24: ▎ CATATAN MANAJEMEN
B26: =CONCATENATE("• Total anggaran proyek sebesar ",TEXT(D21,"""Rp""#,##0")," dengan realisasi ",TEXT(E21,"""Rp""#,##0")," (",TEXT(G21,"0.0%")," dari plafon).")
B27: =CONCATENATE("• Sisa anggaran tersedia: ",TEXT(F21,"""Rp""#,##0"),".")
B28: =CONCATENATE("• Status keseluruhan: ",H21,".")
B29: =CONCATENATE("• Estimasi profit bersih: ",TEXT('Profil Proyek'!D11,"""Rp""#,##0")," (ROI: ",TEXT(IFERROR('Profil Proyek'!D11/'Profil Proyek'!D21,0),"0.0%"),").")
B30: • [Tambahkan catatan manual: penjelasan deviasi, mitigasi risiko, atau rencana tindak lanjut.]
B33: Disusun oleh, | D33: Diperiksa oleh, | F33: Disetujui oleh,
B35: (______________________) | D35: (______________________) | F35: (______________________)
B36: Penyusun Laporan | D36: Manajer Keuangan | F36: Direktur Utama

Sheet Anggaran vs Realisasi
B2: ANGGARAN vs REALISASI
B5: Dompet | C5: Sumber Anggaran | D5: Anggaran (Rp) | E5: Realisasi (Rp) | F5: Varians (Rp) | G5: % Pakai | H5: Status | I5: Komentar
B6: Utama | C6: Limit Lelang + Spare Bidding + Biaya Eksekusi | D6: ='Dompet Utama'!E5 | E6: ='Dompet Utama'!E6 | F6: =D6-E6 | G6: =IFERROR(E6/D6,0) | H6: =IF(D6=0,"-",IF(E6>D6,"OVER BUDGET",IF(E6/D6>=0.9,"WASPADA","AMAN"))) | I6: [Isi catatan]
B7: Dokumen | C7: Biaya Balik Nama (Notaris, BPN, Pajak) | D7: ='Dompet Dokumen'!E5 | E7: ='Dompet Dokumen'!E6 | F7: =D7-E7 | G7: =IFERROR(E7/D7,0) | H7: =IF(D7=0,"-",IF(E7>D7,"OVER BUDGET",IF(E7/D7>=0.9,"WASPADA","AMAN"))) | I7: [Isi catatan]
B8: Renovasi | C8: Renovasi & Peningkatan Properti | D8: ='Dompet Renovasi'!E5 | E8: ='Dompet Renovasi'!E6 | F8: =D8-E8 | G8: =IFERROR(E8/D8,0) | H8: =IF(D8=0,"-",IF(E8>D8,"OVER BUDGET",IF(E8/D8>=0.9,"WASPADA","AMAN"))) | I8: [Isi catatan]
B9: Cadangan | C9: Dana Cadangan / Kontingensi | D9: ='Dompet Cadangan'!E5 | E9: ='Dompet Cadangan'!E6 | F9: =D9-E9 | G9: =IFERROR(E9/D9,0) | H9: =IF(D9=0,"-",IF(E9>D9,"OVER BUDGET",IF(E9/D9>=0.9,"WASPADA","AMAN"))) | I9: [Isi catatan]
B10: TOTAL | C10: Seluruh Dompet | D10: =SUM(D6:D9) | E10: =SUM(E6:E9) | F10: =D10-E10 | G10: =IFERROR(E10/D10,0) | H10: =IF(D10=0,"-",IF(E10>D10,"OVER BUDGET",IF(E10/D10>=0.9,"WASPADA","AMAN"))) | I10: —
B13: ▎ VISUALISASI

Sheet Cashflow Timeline
B2: CASHFLOW TIMELINE — SEMUA DOMPET KRONOLOGIS
B4: Sumber: project_arus_kas (semua wallet, urut tanggal_transaksi ASC)
B6: No. | C6: Tanggal | D6: ID Project | E6: Jenis | F6: Kategori | G6: Nominal (Rp) | H6: Wallet | I6: Judul Transaksi | J6: Status | K6: Catatan | L6: Saldo Berjalan
B7: =IF(C7="","",ROW()-6) | L7: =IF(G7="","",IF(E7="pemasukan",G7,-G7))
B8: =IF(C8="","",ROW()-6) | L8: =IF(G8="","",L7+IF(E8="pemasukan",G8,-G8))
B9: =IF(C9="","",ROW()-6) | L9: =IF(G9="","",L8+IF(E9="pemasukan",G9,-G9))
B10: =IF(C10="","",ROW()-6) | L10: =IF(G10="","",L9+IF(E10="pemasukan",G10,-G10))
B11: =IF(C11="","",ROW()-6) | L11: =IF(G11="","",L10+IF(E11="pemasukan",G11,-G11))
B12: =IF(C12="","",ROW()-6) | L12: =IF(G12="","",L11+IF(E12="pemasukan",G12,-G12))
B13: =IF(C13="","",ROW()-6) | L13: =IF(G13="","",L12+IF(E13="pemasukan",G13,-G13))
B14: =IF(C14="","",ROW()-6) | L14: =IF(G14="","",L13+IF(E14="pemasukan",G14,-G14))
B15: =IF(C15="","",ROW()-6) | L15: =IF(G15="","",L14+IF(E15="pemasukan",G15,-G15))
B16: =IF(C16="","",ROW()-6) | L16: =IF(G16="","",L15+IF(E16="pemasukan",G16,-G16))
B17: =IF(C17="","",ROW()-6) | L17: =IF(G17="","",L16+IF(E17="pemasukan",G17,-G17))
B18: =IF(C18="","",ROW()-6) | L18: =IF(G18="","",L17+IF(E18="pemasukan",G18,-G18))
B19: =IF(C19="","",ROW()-6) | L19: =IF(G19="","",L18+IF(E19="pemasukan",G19,-G19))
... B106: =IF(C106="","",ROW()-6) | L106: =IF(G106="","",L105+IF(E106="pemasukan",G106,-G106))
B108: TOTAL | G108: =SUMPRODUCT((E7:E106="pemasukan")*G7:G106)-SUMPRODUCT((E7:E106="pengeluaran")*G7:G106) | H108: Net | I108: Saldo akhir → | L108: =L106
B110: Petunjuk Export: Tanggal=tanggal_transaksi, ID=id_project, Jenis=jenis_transaksi, Kategori=kategori_transaksi, Nominal=nominal, Wallet=wallet_key, Judul=judul_transaksi, Status=status_transaksi, Catatan=catatan. Order by tanggal_transaksi ASC.

Sheet Dompet Utama
B2: DOMPET UTAMA
B5: Anggaran | E5: 0 | G5: Sisa | I5: =E5-E6
B6: Realisasi | E6: =SUMPRODUCT(('Cashflow Timeline'!H7:H106="utama")*('Cashflow Timeline'!E7:E106="pengeluaran")*'Cashflow Timeline'!G7:G106) | G6: % Penyerapan | I6: =IFERROR(E6/E5,0)
B8: Sumber Anggaran: Limit Lelang + Spare Bidding + Biaya Eksekusi • Wallet Key: 'utama' • Realisasi otomatis dari Cashflow Timeline
B10: ▎ DETAIL TRANSAKSI (filter wallet)
B11: No. | C11: Tanggal | D11: Jenis | E11: Kategori | F11: Judul Transaksi | G11: Nominal (Rp) | H11: Status | I11: Catatan
B12: =IF(C12="","",ROW()-11)
B13: =IF(C13="","",ROW()-11)
B14: =IF(C14="","",ROW()-11)
B15: =IF(C15="","",ROW()-11)
B16: =IF(C16="","",ROW()-11)
B17: =IF(C17="","",ROW()-11)
B18: =IF(C18="","",ROW()-11)
B19: =IF(C19="","",ROW()-11)
B20: =IF(C20="","",ROW()-11)
B21: =IF(C21="","",ROW()-11)
B22: =IF(C22="","",ROW()-11)
B23: =IF(C23="","",ROW()-11)
... B61: =IF(C61="","",ROW()-11)
B62: SUBTOTAL PENGELUARAN | G62: =SUMIFS(G12:G61,D12:D61,"pengeluaran")
B64: Catatan: Sel BIRU = data dari project_arus_kas WHERE wallet_key='utama'. Realisasi di KPI atas dihitung otomatis dari Cashflow Timeline.

Sheet Dompet Dokumen
B2: DOMPET DOKUMEN
B5: Anggaran | E5: 0 | G5: Sisa | I5: =E5-E6
B6: Realisasi | E6: =SUMPRODUCT(('Cashflow Timeline'!H7:H106="dokumen")*('Cashflow Timeline'!E7:E106="pengeluaran")*'Cashflow Timeline'!G7:G106) | G6: % Penyerapan | I6: =IFERROR(E6/E5,0)
B8: Sumber Anggaran: Biaya Balik Nama (Notaris, BPN, Pajak) • Wallet Key: 'dokumen' • Realisasi otomatis dari Cashflow Timeline
B10: ▎ DETAIL TRANSAKSI (filter wallet)
B11: No. | C11: Tanggal | D11: Jenis | E11: Kategori | F11: Judul Transaksi | G11: Nominal (Rp) | H11: Status | I11: Catatan
B12: =IF(C12="","",ROW()-11)
B13: =IF(C13="","",ROW()-11)
B14: =IF(C14="","",ROW()-11)
B15: =IF(C15="","",ROW()-11)
B16: =IF(C16="","",ROW()-11)
B17: =IF(C17="","",ROW()-11)
B18: =IF(C18="","",ROW()-11)
B19: =IF(C19="","",ROW()-11)
B20: =IF(C20="","",ROW()-11)
B21: =IF(C21="","",ROW()-11)
B22: =IF(C22="","",ROW()-11)
B23: =IF(C23="","",ROW()-11)
... B61: =IF(C61="","",ROW()-11)
B62: SUBTOTAL PENGELUARAN | G62: =SUMIFS(G12:G61,D12:D61,"pengeluaran")
B64: Catatan: Sel BIRU = data dari project_arus_kas WHERE wallet_key='dokumen'. Realisasi di KPI atas dihitung otomatis dari Cashflow Timeline.

Sheet Dompet Eksekusi
B2: DOMPET EKSEKUSI
B5: Anggaran | E5: 0 | G5: Sisa | I5: 0
B6: Realisasi | E6: 0 | G6: % Penyerapan | I6: 0
B8: Sumber Anggaran: Biaya Eksekusi • Wallet Key: 'eksekusi' • Realisasi otomatis dari Cashflow Timeline
B10: ▎ DETAIL TRANSAKSI (filter wallet)
B11: No. | C11: Tanggal | D11: Jenis | E11: Kategori | F11: Judul Transaksi | G11: Nominal (Rp) | H11: Status | I11: Catatan
B62: SUBTOTAL PENGELUARAN | G62: 0
B64: Catatan: Sel BIRU = data dari project_arus_kas WHERE wallet_key='eksekusi'. Realisasi di KPI atas dihitung otomatis dari Cashflow Timeline.

Sheet Dompet Renovasi
B2: DOMPET RENOVASI
B5: Anggaran | E5: 0 | G5: Sisa | I5: =E5-E6
B6: Realisasi | E6: =SUMPRODUCT(('Cashflow Timeline'!H7:H106="renovasi")*('Cashflow Timeline'!E7:E106="pengeluaran")*'Cashflow Timeline'!G7:G106) | G6: % Penyerapan | I6: =IFERROR(E6/E5,0)
B8: Sumber Anggaran: Renovasi & Peningkatan Properti • Wallet Key: 'renovasi' • Realisasi otomatis dari Cashflow Timeline
B10: ▎ DETAIL TRANSAKSI (filter wallet)
B11: No. | C11: Tanggal | D11: Jenis | E11: Kategori | F11: Judul Transaksi | G11: Nominal (Rp) | H11: Status | I11: Catatan
B12: =IF(C12="","",ROW()-11)
B13: =IF(C13="","",ROW()-11)
B14: =IF(C14="","",ROW()-11)
B15: =IF(C15="","",ROW()-11)
B16: =IF(C16="","",ROW()-11)
B17: =IF(C17="","",ROW()-11)
B18: =IF(C18="","",ROW()-11)
B19: =IF(C19="","",ROW()-11)
B20: =IF(C20="","",ROW()-11)
B21: =IF(C21="","",ROW()-11)
B22: =IF(C22="","",ROW()-11)
B23: =IF(C23="","",ROW()-11)
... B61: =IF(C61="","",ROW()-11)
B62: SUBTOTAL PENGELUARAN | G62: =SUMIFS(G12:G61,D12:D61,"pengeluaran")
B64: Catatan: Sel BIRU = data dari project_arus_kas WHERE wallet_key='renovasi'. Realisasi di KPI atas dihitung otomatis dari Cashflow Timeline.

Sheet Dompet Cadangan
B2: DOMPET CADANGAN
B5: Anggaran | E5: 0 | G5: Sisa | I5: =E5-E6
B6: Realisasi | E6: =SUMPRODUCT(('Cashflow Timeline'!H7:H106="cadangan")*('Cashflow Timeline'!E7:E106="pengeluaran")*'Cashflow Timeline'!G7:G106) | G6: % Penyerapan | I6: =IFERROR(E6/E5,0)
B8: Sumber Anggaran: Dana Cadangan / Kontingensi • Wallet Key: 'cadangan' • Realisasi otomatis dari Cashflow Timeline
B10: ▎ DETAIL TRANSAKSI (filter wallet)
B11: No. | C11: Tanggal | D11: Jenis | E11: Kategori | F11: Judul Transaksi | G11: Nominal (Rp) | H11: Status | I11: Catatan
B12: =IF(C12="","",ROW()-11)
B13: =IF(C13="","",ROW()-11)
B14: =IF(C14="","",ROW()-11)
B15: =IF(C15="","",ROW()-11)
B16: =IF(C16="","",ROW()-11)
B17: =IF(C17="","",ROW()-11)
B18: =IF(C18="","",ROW()-11)
B19: =IF(C19="","",ROW()-11)
B20: =IF(C20="","",ROW()-11)
B21: =IF(C21="","",ROW()-11)
B22: =IF(C22="","",ROW()-11)
B23: =IF(C23="","",ROW()-11)
... B61: =IF(C61="","",ROW()-11)
B62: SUBTOTAL PENGELUARAN | G62: =SUMIFS(G12:G61,D12:D61,"pengeluaran")
B64: Catatan: Sel BIRU = data dari project_arus_kas WHERE wallet_key='cadangan'. Realisasi di KPI atas dihitung otomatis dari Cashflow Timeline.

Sheet Breakdown Kategori
B2: BREAKDOWN PENGELUARAN PER KATEGORI
B4: Otomatis terhitung dari Cashflow Timeline (jenis = pengeluaran)
B6: Kategori | C6: Total Pengeluaran (Rp) | D6: % dari Total
B7: Pendanaan Investor | C7: =SUMPRODUCT(('Cashflow Timeline'!F7:F106="pendanaan_investor")*('Cashflow Timeline'!E7:E106="pengeluaran")*'Cashflow Timeline'!G7:G106) | D7: =IFERROR(C7/$C$18,0)
B8: Modal Internal | C8: =SUMPRODUCT(('Cashflow Timeline'!F7:F106="modal_internal")*('Cashflow Timeline'!E7:E106="pengeluaran")*'Cashflow Timeline'!G7:G106) | D8: =IFERROR(C8/$C$18,0)
B9: Pengembalian Modal | C9: =SUMPRODUCT(('Cashflow Timeline'!F7:F106="pengembalian_modal")*('Cashflow Timeline'!E7:E106="pengeluaran")*'Cashflow Timeline'!G7:G106) | D9: =IFERROR(C9/$C$18,0)
B10: Pembayaran Lelang | C10: =SUMPRODUCT(('Cashflow Timeline'!F7:F106="bayar_lelang")*('Cashflow Timeline'!E7:E106="pengeluaran")*'Cashflow Timeline'!G7:G106) | D10: =IFERROR(C10/$C$18,0)
B11: Biaya Eksekusi | C11: =SUMPRODUCT(('Cashflow Timeline'!F7:F106="biaya_eksekusi")*('Cashflow Timeline'!E7:E106="pengeluaran")*'Cashflow Timeline'!G7:G106) | D11: =IFERROR(C11/$C$18,0)
B12: Balik Nama | C12: =SUMPRODUCT(('Cashflow Timeline'!F7:F106="balik_nama")*('Cashflow Timeline'!E7:E106="pengeluaran")*'Cashflow Timeline'!G7:G106) | D12: =IFERROR(C12/$C$18,0)
B13: Renovasi | C13: =SUMPRODUCT(('Cashflow Timeline'!F7:F106="renovasi")*('Cashflow Timeline'!E7:E106="pengeluaran")*'Cashflow Timeline'!G7:G106) | D13: =IFERROR(C13/$C$18,0)
B14: Operasional | C14: =SUMPRODUCT(('Cashflow Timeline'!F7:F106="operasional")*('Cashflow Timeline'!E7:E106="pengeluaran")*'Cashflow Timeline'!G7:G106) | D14: =IFERROR(C14/$C$18,0)
B15: Pengeluaran Lainnya | C15: =SUMPRODUCT(('Cashflow Timeline'!F7:F106="pengeluaran_lain")*('Cashflow Timeline'!E7:E106="pengeluaran")*'Cashflow Timeline'!G7:G106) | D15: =IFERROR(C15/$C$18,0)
B16: Penjualan Properti | C16: =SUMPRODUCT(('Cashflow Timeline'!F7:F106="pemasukan_penjualan")*('Cashflow Timeline'!E7:E106="pengeluaran")*'Cashflow Timeline'!G7:G106) | D16: =IFERROR(C16/$C$18,0)
B17: Pemasukan Lainnya | C17: =SUMPRODUCT(('Cashflow Timeline'!F7:F106="pemasukan_lain")*('Cashflow Timeline'!E7:E106="pengeluaran")*'Cashflow Timeline'!G7:G106) | D17: =IFERROR(C17/$C$18,0)
B18: TOTAL PENGELUARAN | C18: =SUM(C7:C17) | D18: 100.0%

Sheet Petunjuk
B2: PETUNJUK PENGGUNAAN TEMPLATE
B5: ▸ | C5: Cover
C6: Halaman identitas. Diisi dari tabel project. KPI di bawah otomatis dari sheet Profil Proyek.
B8: ▸ | C8: Profil Proyek
C9: Detail valuasi & breakdown biaya akuisisi dari tabel project. Lengkap dengan chart ROI dan 3 KPI Margin/ROI/Markup.
B11: ▸ | C11: Ringkasan Eksekutif
C12: Halaman utama investor. 4 KPI Anggaran + 3 KPI Cashflow + ringkasan per dompet dengan status otomatis. Catatan manajemen otomatis terisi.
B14: ▸ | C14: Anggaran vs Realisasi
C15: Analisis varians 4 dompet + 2 chart (Bar comparison & Pie komposisi).
B17: ▸ | C17: Cashflow Timeline
C18: MASTER TABLE — semua transaksi dari project_arus_kas, kronologis. 100 baris siap pakai. Saldo Berjalan otomatis. Mapping kolom di footer.
B20: ▸ | C20: Dompet Utama / Dokumen / Renovasi / Cadangan
C21: Detail per dompet. Anggaran (E5) diisi dari mapping (Utama=limit+spare+eksekusi, Dokumen=balik_nama, Renovasi=biaya_renov, Cadangan=dana_cadangan). Realisasi otomatis dari Cashflow Timeline filter wallet_key.
B23: ▸ | C23: Breakdown Kategori
C24: Pie chart komposisi pengeluaran per kategori_transaksi. Otomatis dari Cashflow Timeline.
B26: ▸ | C26: Color Coding
C27: Sel BIRU = data dari database. Sel HITAM = formula otomatis. Status: HIJAU=Aman (<90%), KUNING=Waspada (90-100%), MERAH=Over Budget (>100%). Jenis: HIJAU=pemasukan, MERAH=pengeluaran.
B29: ▸ | C29: Untuk Pengembang Program — Mapping Export
C30: (1) Cover D9 = id_project. (2) Profil Proyek D9-D11 = harga_pembelian, estimasi_harga_jual, estimasi_profit_bersih. D15-D20 = nilai_limit_lelang, spare_bidding, biaya_eksekusi, biaya_balik_nama, biaya_renov, dana_cadangan. D24-D25 = target_pendanaan, total_pendanaan. (3) Setiap 'Dompet [Nama]'!E5 = jumlah komponen biaya sesuai mapping. (4) Cashflow Timeline rows 7-106 = SELECT * FROM project_arus_kas WHERE id_project=? ORDER BY tanggal_transaksi ASC.
